tinder/__init__.py
tinder/batch.py
tinder/boost.py
tinder/config.py
tinder/dataset.py
tinder/image.py
tinder/kaggle.py
tinder/metrics.py
tinder/model.py
tinder/monitor.py
tinder/nn.py
tinder/optimizer.py
tinder/queue.py
tinder/rl.py
tinder/saver.py
tinder/utils.py
tinder/visualize.py
tinder/test/__init__.py
tinder/test/test_basic.py
tinder/test/test_batch.py
tinder/test/test_config.py
tinder/test/test_dataset.py
tinder/test/test_metrics.py
tinder/test/test_serving.py
tinder/vendor/__init__.py
tinder/vendor/backtrace.py
tinder-0.1.9.dist-info/LICENSE.txt
tinder-0.1.9.dist-info/METADATA
tinder-0.1.9.dist-info/WHEEL
tinder-0.1.9.dist-info/top_level.txt
tinder-0.1.9.dist-info/RECORD
